stdlib_list/__init__.py
stdlib_list/_version.py
stdlib_list/base.py
stdlib_list/fetch.py
stdlib_list/lists/2.6.txt
stdlib_list/lists/2.7.txt
stdlib_list/lists/3.2.txt
stdlib_list/lists/3.3.txt
stdlib_list/lists/3.4.txt
stdlib_list/lists/3.5.txt
stdlib_list/lists/3.6.txt
stdlib_list/lists/3.7.txt
stdlib_list/lists/3.8.txt
stdlib_list/lists/3.9.txt
stdlib_list-0.7.0.dist-info/LICENSE
stdlib_list-0.7.0.dist-info/METADATA
stdlib_list-0.7.0.dist-info/WHEEL
stdlib_list-0.7.0.dist-info/top_level.txt
stdlib_list-0.7.0.dist-info/RECORD
