Metadata-Version: 2.1
Name: stdlib-list
Version: 0.7.0
Summary: A list of Python Standard Libraries (2.6-7, 3.2-8).
Home-page: https://github.com/jackmaney/python-stdlib-list
Author: Jack Maney
Author-email: jackmaney@gmail.com
License: MIT
Platform: UNKNOWN
Provides-Extra: develop
